skfda/__init__.py
skfda/py.typed
skfda/_utils/__init__.py
skfda/_utils/_neighbors_base.py
skfda/_utils/_sklearn_adapter.py
skfda/_utils/_utils.py
skfda/_utils/_warping.py
skfda/_utils/constants.py
skfda/_utils/ndfunction/__init__.py
skfda/_utils/ndfunction/_functions.py
skfda/datasets/__init__.py
skfda/datasets/_real_datasets.py
skfda/datasets/_samples_generators.py
skfda/exploratory/__init__.py
skfda/exploratory/depth/__init__.py
skfda/exploratory/depth/_depth.py
skfda/exploratory/depth/multivariate.py
skfda/exploratory/outliers/__init__.py
skfda/exploratory/outliers/_boxplot.py
skfda/exploratory/outliers/_directional_outlyingness.py
skfda/exploratory/outliers/_directional_outlyingness_experiment_results.py
skfda/exploratory/outliers/_envelopes.py
skfda/exploratory/outliers/_outliergram.py
skfda/exploratory/outliers/neighbors_outlier.py
skfda/exploratory/stats/__init__.py
skfda/exploratory/stats/_fisher_rao.py
skfda/exploratory/stats/_stats.py
skfda/exploratory/stats/covariance/__init__.py
skfda/exploratory/stats/covariance/_base.py
skfda/exploratory/stats/covariance/_empirical.py
skfda/exploratory/stats/covariance/_parametric_gaussian.py
skfda/exploratory/visualization/__init__.py
skfda/exploratory/visualization/_baseplot.py
skfda/exploratory/visualization/_boxplot.py
skfda/exploratory/visualization/_ddplot.py
skfda/exploratory/visualization/_magnitude_shape_plot.py
skfda/exploratory/visualization/_multiple_display.py
skfda/exploratory/visualization/_outliergram.py
skfda/exploratory/visualization/_parametric_plot.py
skfda/exploratory/visualization/_utils.py
skfda/exploratory/visualization/clustering.py
skfda/exploratory/visualization/fpca.py
skfda/exploratory/visualization/representation.py
skfda/inference/__init__.py
skfda/inference/anova/__init__.py
skfda/inference/anova/_anova_oneway.py
skfda/inference/hotelling/__init__.py
skfda/inference/hotelling/_hotelling.py
skfda/misc/__init__.py
skfda/misc/_math.py
skfda/misc/covariances.py
skfda/misc/hat_matrix.py
scikit_fda-0.9.1.dist-info/LICENSE.txt
scikit_fda-0.9.1.dist-info/METADATA
scikit_fda-0.9.1.dist-info/WHEEL
scikit_fda-0.9.1.dist-info/top_level.txt
scikit_fda-0.9.1.dist-info/RECORD
