Metadata-Version: 2.1
Name: scikit-fda
Version: 0.9.1
Summary: Functional Data Analysis Python package.
Maintainer-email: Carlos Ramos Carreño <vnmabus@gmail.com>
License: BSD 3-Clause License
Project-URL: homepage, https://github.com/GAA-UAM/scikit-fda
Project-URL: documentation, https://fda.readthedocs.io
Project-URL: repository, https://github.com/GAA-UAM/scikit-fda
Keywords: functional data,statistics,machine learning
Classifier: Development Status :: 4 - Beta
Classifier: Intended Audience :: Developers
Classifier: Intended Audience :: Science/Research
Classifier: License :: OSI Approved :: BSD License
Classifier: Natural Language :: English
Classifier: Operating System :: OS Independent
Classifier: Programming Language :: Python :: 3
Classifier: Programming Language :: Python :: 3.9
Classifier: Topic :: Scientific/Engineering :: Mathematics
Classifier: Topic :: Software Development :: Libraries :: Python Modules
Classifier: Typing :: Typed
Requires-Python: >=3.9
License-File: LICENSE.txt
Requires-Dist: dcor
Requires-Dist: fdasrsf!=2.5.7,>=2.2.0
Requires-Dist: findiff
Requires-Dist: lazy_loader
Requires-Dist: matplotlib
Requires-Dist: multimethod!=1.11,!=1.11.1,>=1.5
Requires-Dist: numpy>=1.16
Requires-Dist: pandas>=1.0
Requires-Dist: rdata
Requires-Dist: scikit-datasets[cran]>=0.1.24
Requires-Dist: scikit-learn>=0.20
Requires-Dist: scipy>=1.3.0
Requires-Dist: typing-extensions
Provides-Extra: docs
Requires-Dist: cartopy; extra == "docs"
Requires-Dist: ipykernel; extra == "docs"
Requires-Dist: jupyter-sphinx; extra == "docs"
Requires-Dist: myst-parser; extra == "docs"
Requires-Dist: pillow; extra == "docs"
Requires-Dist: pydata-sphinx-theme; extra == "docs"
Requires-Dist: pytest; extra == "docs"
Requires-Dist: setuptools>=41.2; extra == "docs"
Requires-Dist: sphinx>=3; extra == "docs"
Requires-Dist: sphinx-gallery; extra == "docs"
Requires-Dist: sphinxcontrib-bibtex; extra == "docs"
Provides-Extra: test
Requires-Dist: pytest; extra == "test"
Requires-Dist: pytest-env; extra == "test"
Requires-Dist: pytest-subtests; extra == "test"
Requires-Dist: scipy<1.11.0; extra == "test"
